differint/__init__.py
differint/differint.py
differint-1.0.0.dist-info/LICENSE
differint-1.0.0.dist-info/METADATA
differint-1.0.0.dist-info/WHEEL
differint-1.0.0.dist-info/top_level.txt
differint-1.0.0.dist-info/RECORD
