Metadata-Version: 2.1
Name: differint
Version: 1.0.0
Summary: Collection of algorithms for numerically calculating fractional derivatives.
Home-page: http://github.com/differint/differint
Author: Matthew Adams
Author-email: Matthew.Adams@ucalgary.ca
License: MIT
Classifier: Development Status :: 4 - Beta
Classifier: License :: OSI Approved :: MIT License
Classifier: Programming Language :: Python :: 3.3
Classifier: Intended Audience :: Science/Research
Classifier: Topic :: Scientific/Engineering :: Mathematics
Classifier: Programming Language :: Python :: 3.3
Classifier: Programming Language :: Python :: 3.4
Classifier: Programming Language :: Python :: 3.5
License-File: LICENSE
Requires-Dist: numpy
